eth_keys/__init__.py
ethereum_keys-0.1.0a9.dist-info/DESCRIPTION.rst
ethereum_keys-0.1.0a9.dist-info/METADATA
ethereum_keys-0.1.0a9.dist-info/RECORD
ethereum_keys-0.1.0a9.dist-info/WHEEL
ethereum_keys-0.1.0a9.dist-info/metadata.json
ethereum_keys-0.1.0a9.dist-info/top_level.txt
